llm_resource_finder/__init__.py
llm_resource_finder/main.py
llm_resource_finder/prompts.py
llm_resource_finder-2025.12.20202112.dist-info/METADATA
llm_resource_finder-2025.12.20202112.dist-info/WHEEL
llm_resource_finder-2025.12.20202112.dist-info/top_level.txt
llm_resource_finder-2025.12.20202112.dist-info/RECORD
