Metadata-Version: 2.4
Name: llm-resource-finder
Version: 2025.12.20202112
Summary: A new package that helps users discover and access the latest free LLM (Large Language Model) resources. Users can input their specific needs or interests, and the package will return a structured lis
Author-email: llm-resource-finder <hi@eugene.plus>
License: MIT
Project-URL: Homepage, https://github.com/chigwell/llm-resource-finder
Requires-Python: >=3.9
Requires-Dist: langchain-llm7>=0.0.0
Requires-Dist: llmatch-messages>=0.0.0
Requires-Dist: langchain-core>=0.3.0
